pathlib_revised/__init__.py
pathlib_revised/dir_entry_path.py
pathlib_revised/pathlib.py
pathlib_revised/tests/__init__.py
pathlib_revised/tests/base.py
pathlib_revised/tests/test_dir_entry_path.py
pathlib_revised/tests/test_pathlib2.py
pathlib_revised-0.1.0.dist-info/DESCRIPTION.rst
pathlib_revised-0.1.0.dist-info/METADATA
pathlib_revised-0.1.0.dist-info/RECORD
pathlib_revised-0.1.0.dist-info/WHEEL
pathlib_revised-0.1.0.dist-info/metadata.json
pathlib_revised-0.1.0.dist-info/top_level.txt
