Metadata-Version: 2.0
Name: pathlib-revised
Version: 0.1.0
Summary: pathlib_revised is a enhanced version of pathlib
Home-page: https://github.com/jedie/pathlib_revised
Author: Jens Diemer
Author-email: UNKNOWN
License: GNU General Public License (GNU GPL v3 or above)
Keywords: pathlib Windows Linux
Platform: UNKNOWN
Classifier: Development Status :: 4 - Beta
Classifier: Intended Audience :: Developers
Classifier: License :: OSI Approved :: GNU General Public License (GPL)
Classifier: Programming Language :: Python :: 3.4
Classifier: Programming Language :: Python :: 3.5
Classifier: Programming Language :: Python :: 3 :: Only
Classifier: Operating System :: OS Independent
Classifier: Topic :: Software Development
Classifier: Topic :: Software Development :: Libraries
Classifier: Topic :: Software Development :: Libraries :: Python Modules
Requires-Dist: scandir; python_version=="3.4"
